jabs_postprocess/__init__.py
jabs_postprocess/bouts_to_bins.py
jabs_postprocess/compare_gt.py
jabs_postprocess/create_video_snippets.py
jabs_postprocess/generate_behavior_tables.py
jabs_postprocess/heuristic_classify.py
jabs_postprocess/analysis_utils/__init__.py
jabs_postprocess/analysis_utils/clip_utils.py
jabs_postprocess/analysis_utils/parse_table.py
jabs_postprocess/analysis_utils/plots.py
jabs_postprocess/analysis_utils/qc_plots.py
jabs_postprocess/cli/__init__.py
jabs_postprocess/cli/main.py
jabs_postprocess/cli/utils.py
jabs_postprocess/utils/__init__.py
jabs_postprocess/utils/features.py
jabs_postprocess/utils/heuristics.py
jabs_postprocess/utils/identity.py
jabs_postprocess/utils/metadata.py
jabs_postprocess/utils/project_utils.py
jabs_postprocess-0.5.4.dist-info/licenses/LICENSE
jabs_postprocess-0.5.4.dist-info/METADATA
jabs_postprocess-0.5.4.dist-info/WHEEL
jabs_postprocess-0.5.4.dist-info/entry_points.txt
jabs_postprocess-0.5.4.dist-info/top_level.txt
jabs_postprocess-0.5.4.dist-info/RECORD
