Metadata-Version: 2.4
Name: jabs-postprocess
Version: 0.5.4
Summary: A python library for JABS postprocessing utilities.
License-Expression: LicenseRef-PLATFORM-LICENSE-AGREEMENT-FOR-NON-COMMERCIAL-USE
Project-URL: repository, https://github.com/KumarLabJax/JABS-postprocess
Requires-Python: >=3.10
License-File: LICENSE
Requires-Dist: black>=23.9.1
Requires-Dist: h5py>=3.13.0
Requires-Dist: imageio>=2.31.3
Requires-Dist: imageio-ffmpeg>=0.4.9
Requires-Dist: matplotlib>=3.8.0
Requires-Dist: mizani>=0.9.3
Requires-Dist: numpy>=2.2.5
Requires-Dist: opencv-python-headless>=4.8.0.76
Requires-Dist: openpyxl>=3.1.2
Requires-Dist: pandas>=2.2.3
Requires-Dist: pydocstyle>=6.3.0
Requires-Dist: plotnine>=0.14.5
Requires-Dist: pyqt5>=5.15.2
Requires-Dist: pyyaml>=6.0.2
Requires-Dist: Pillow>=10.0.1
Requires-Dist: scikit-learn>=1.6.1
Requires-Dist: scipy>=1.15.2
Requires-Dist: typer>=0.20.0
Dynamic: license-file
